labelprinterkit/__init__.py
labelprinterkit/backends/__init__.py
labelprinterkit/backends/bluetooth.py
labelprinterkit/backends/network.py
labelprinterkit/backends/usb.py
labelprinterkit/constants.py
labelprinterkit/job.py
labelprinterkit/label.py
labelprinterkit/page.py
labelprinterkit/printers.py
labelprinterkit-0.7.1.dist-info/LICENSE
labelprinterkit-0.7.1.dist-info/METADATA
labelprinterkit-0.7.1.dist-info/WHEEL
labelprinterkit-0.7.1.dist-info/RECORD
