Metadata-Version: 2.1
Name: labelprinterkit
Version: 0.7.1
Summary: A library for creating and printing labels for Brother P-Touch devices
License: Apache License, Version 2.0
Author: Adrian Tschira
Author-email: packages@notafile.com
Requires-Python: >=3.9,<4.0
Classifier: License :: Other/Proprietary License
Classifier: Programming Language :: Python :: 3
Classifier: Programming Language :: Python :: 3.9
Classifier: Programming Language :: Python :: 3.10
Classifier: Programming Language :: Python :: 3.11
Provides-Extra: bluetooth
Provides-Extra: qrcode
Provides-Extra: snmp
Requires-Dist: packbits (>=0.6,<0.7)
Requires-Dist: pillow (>=9.5.0,<10.0.0)
Requires-Dist: pyasn1 (>=0.4.8,<0.5.0) ; extra == "snmp"
Requires-Dist: pyserial (>=3.5,<4.0) ; extra == "bluetooth"
Requires-Dist: pysnmp (>=4.4.12,<5.0.0) ; extra == "snmp"
Requires-Dist: pyusb (>=1.2.1,<2.0.0)
Requires-Dist: qrcode[pil] (>=7.4.2,<8.0.0) ; extra == "qrcode"
Requires-Dist: setuptools (>=68.0.0,<69.0.0)
